{
  "annotations": {
    "list": [
      {
        "builtIn": 1,
        "datasource": {
          "type": "datasource",
          "uid": "-- Mixed --"
        },
        "enable": true,
        "hide": false,
        "name": "Falco Alerts",
        "type": "tags",
        "iconColor": "rgba(255, 99, 132, 1)",
        "target": {
          "limit": 100,
          "matchAny": false,
          "tags": [],
          "type": "dashboard"
        }
      }
    ]
  },
  "editable": true,
  "fiscalYearStartMonth": 0,
  "graphTooltip": 1,
  "id": 1,
  "links": [],
  "liveNow": false,
  "panels": [
    {
      "collapsed": false,
      "gridPos": {
        "h": 8,
        "w": 12,
        "x": 0,
        "y": 0
      },
      "id": 1,
      "title": "Application Request Rate",
      "type": "timeseries",
      "datasource": {
        "type": "prometheus",
        "uid": "prometheus"
      },
      "targets": [
        {
          "datasource": {
            "type": "prometheus",
            "uid": "prometheus"
          },
          "editorMode": "code",
          "expr": "sum(rate(http_requests_total[5m])) by (status, endpoint)",
          "legendFormat": "{{status}} - {{endpoint}}",
          "range": true,
          "refId": "A"
        }
      ],
      "fieldConfig": {
        "defaults": {
          "custom": {
            "drawStyle": "line",
            "lineInterpolation": "smooth"
          },
          "unit": "reqps"
        }
      }
    },
    {
      "collapsed": false,
      "gridPos": {
        "h": 8,
        "w": 12,
        "x": 12,
        "y": 0
      },
      "id": 2,
      "title": "Falco Security Alerts Over Time",
      "type": "timeseries",
      "datasource": {
        "type": "prometheus",
        "uid": "prometheus"
      },
      "targets": [
        {
          "datasource": {
            "type": "prometheus",
            "uid": "prometheus"
          },
          "editorMode": "code",
          "expr": "sum(rate(falco_events_total[5m])) by (rule, priority)",
          "legendFormat": "{{priority}}: {{rule}}",
          "range": true,
          "refId": "A"
        }
      ],
      "fieldConfig": {
        "defaults": {
          "custom": {
            "drawStyle": "bars",
            "fillOpacity": 80
          },
          "unit": "alerts"
        }
      }
    },
    {
      "collapsed": false,
      "gridPos": {
        "h": 8,
        "w": 24,
        "x": 0,
        "y": 8
      },
      "id": 3,
      "title": "Correlated Attack Visualization (95th percentile latency vs Security Events)",
      "type": "timeseries",
      "datasource": {
        "type": "prometheus",
        "uid": "prometheus"
      },
      "targets": [
        {
          "datasource": {
            "type": "prometheus",
            "uid": "prometheus"
          },
          "editorMode": "code",
          "expr": "histogram_quantile(0.95, sum(rate(http_request_duration_seconds_bucket[5m])) by (le))",
          "legendFormat": "P95 Latency (seconds)",
          "range": true,
          "refId": "A"
        },
        {
          "datasource": {
            "type": "prometheus",
            "uid": "prometheus"
          },
          "editorMode": "code",
          "expr": "sum(increase(falco_events_total[5m]))",
          "legendFormat": "Falco Security Incidents",
          "range": true,
          "refId": "B"
        }
      ],
      "fieldConfig": {
        "defaults": {
          "custom": {
            "drawStyle": "line",
            "lineInterpolation": "linear"
          }
        }
      }
    }
  ],
  "refresh": "10s",
  "schemaVersion": 38,
  "style": "dark",
  "tags": [
    "security",
    "devsecops",
    "falco",
    "prometheus"
  ],
  "time": {
    "from": "now-1h",
    "to": "now"
  },
  "timepicker": {},
  "timezone": "browser",
  "title": "Falco & App Performance Correlation",
  "version": 1
}
